autocorpus/IAO_dicts/IAO_FINAL_MAPPING.txt
autocorpus/IAO_dicts/IAO_term_to_ID.txt
autocorpus/__init__.py
autocorpus/__main__.py
autocorpus/abbreviation.py
autocorpus/ac_bioc/__init__.py
autocorpus/ac_bioc/annotation.py
autocorpus/ac_bioc/bioctable/__init__.py
autocorpus/ac_bioc/bioctable/cell.py
autocorpus/ac_bioc/bioctable/collection.py
autocorpus/ac_bioc/bioctable/document.py
autocorpus/ac_bioc/bioctable/json.py
autocorpus/ac_bioc/bioctable/passage.py
autocorpus/ac_bioc/bioctable/py.typed
autocorpus/ac_bioc/collection.py
autocorpus/ac_bioc/decoder.py
autocorpus/ac_bioc/document.py
autocorpus/ac_bioc/json.py
autocorpus/ac_bioc/location.py
autocorpus/ac_bioc/node.py
autocorpus/ac_bioc/passage.py
autocorpus/ac_bioc/py.typed
autocorpus/ac_bioc/relation.py
autocorpus/ac_bioc/sentence.py
autocorpus/ac_bioc/xml.py
autocorpus/autocorpus.py
autocorpus/bioc_formatter.py
autocorpus/bioc_passage.py
autocorpus/bioc_supplementary.py
autocorpus/config.py
autocorpus/configs/__init__.py
autocorpus/configs/config_nature_genetics.json
autocorpus/configs/config_plos_genetics.json
autocorpus/configs/config_pmc.json
autocorpus/configs/config_pmc_pre_oct_2024.json
autocorpus/configs/config_template.json
autocorpus/data_structures.py
autocorpus/file_processing.py
autocorpus/file_type.py
autocorpus/html.py
autocorpus/inputs.py
autocorpus/parse_xml.py
autocorpus/pdf.py
autocorpus/py.typed
autocorpus/reference.py
autocorpus/run.py
autocorpus/section.py
autocorpus/table.py
autocorpus/utils.py
autocorpus/word.py
autocorpus-1.1.1.dist-info/LICENSE
autocorpus-1.1.1.dist-info/METADATA
autocorpus-1.1.1.dist-info/WHEEL
autocorpus-1.1.1.dist-info/entry_points.txt
autocorpus-1.1.1.dist-info/RECORD
