Metadata-Version: 2.3
Name: autocorpus
Version: 1.1.1
Summary: A tool to standardise text and table data extracted from full text publications.
License: GPL-3.0-only
Keywords: natural language processing,text mining,biomedical literature,semantics,health data
Author: Tim Beck
Author-email: tim.beck@nottingham.ac.uk
Requires-Python: >=3.10,<4
Classifier: Intended Audience :: Science/Research
Classifier: License :: OSI Approved :: GNU General Public License v3 (GPLv3)
Classifier: Programming Language :: Python :: 3
Classifier: Programming Language :: Python :: 3.10
Classifier: Programming Language :: Python :: 3.11
Classifier: Programming Language :: Python :: 3.12
Classifier: Programming Language :: Python :: 3.13
Provides-Extra: pdf
Requires-Dist: beautifulsoup4 (>=4.12.3,<5.0.0)
Requires-Dist: dataclasses-json (>=0.6.7,<0.7.0)
Requires-Dist: fuzzywuzzy[speedup] (>=0.18.0,<0.19.0)
Requires-Dist: lxml (>=5.3.0,<6.0.0)
Requires-Dist: marker-pdf (>=1.6.2,<2.0.0) ; extra == "pdf"
Requires-Dist: nltk (>=3.9.1,<4.0.0)
Requires-Dist: pandas (>=2.2.3,<3.0.0)
Requires-Dist: python-docx (>=1.1.2,<2.0.0)
Requires-Dist: regex (>=2024.9.11,<2025.0.0)
Project-URL: Documentation, https://omicsnlp.github.io/Auto-CORPus/
Project-URL: Publication, https://doi.org/10.3389/fdgth.2022.788124
Project-URL: Repository, https://github.com/omicsNLP/Auto-CORPus
